gifpy
